pyioneer/__init__.py
pyioneer/batch.py
pyioneer/block_detection.py
pyioneer/cli.py
pyioneer/idealization.py
pyioneer/io.py
pyioneer/utils.py
pyioneer-0.1.0.dist-info/licenses/LICENSE
tests/__init__.py
tests/test_block_detection.py
tests/test_idealization.py
tests/test_io.py
pyioneer-0.1.0.dist-info/METADATA
pyioneer-0.1.0.dist-info/WHEEL
pyioneer-0.1.0.dist-info/entry_points.txt
pyioneer-0.1.0.dist-info/top_level.txt
pyioneer-0.1.0.dist-info/RECORD
