Metadata-Version: 2.4
Name: pyioneer
Version: 0.1.0
Summary: A Python library for idealizing single-channel current recordings
Home-page: https://github.com/Adorey92-git/pyioneer
Author: Adam Dorey
Author-email: Adam Dorey <adamdorey92@gmail.com>
License-Expression: MIT
Project-URL: Homepage, https://github.com/Adorey92-git/pyioneer
Project-URL: Documentation, https://github.com/Adorey92-git/pyioneer
Project-URL: Repository, https://github.com/Adorey92-git/pyioneer
Project-URL: Issues, https://github.com/Adorey92-git/pyioneer/issues
Keywords: electrophysiology,idealization,single-channel,ABF,HMM
Classifier: Development Status :: 3 - Alpha
Classifier: Intended Audience :: Science/Research
Classifier: Topic :: Scientific/Engineering :: Bio-Informatics
Classifier: Programming Language :: Python :: 3
Classifier: Programming Language :: Python :: 3.8
Classifier: Programming Language :: Python :: 3.9
Classifier: Programming Language :: Python :: 3.10
Classifier: Programming Language :: Python :: 3.11
Requires-Python: >=3.8
License-File: LICENSE
Requires-Dist: pyabf>=2.3.8
Requires-Dist: numpy>=1.24.0
Requires-Dist: scipy>=1.10.0
Requires-Dist: click>=8.0.0
Provides-Extra: hmm
Requires-Dist: hmmlearn>=0.2.7; extra == "hmm"
Provides-Extra: changepoint
Requires-Dist: ruptures>=1.1.8; extra == "changepoint"
Provides-Extra: all
Requires-Dist: hmmlearn>=0.2.7; extra == "all"
Requires-Dist: ruptures>=1.1.8; extra == "all"
Requires-Dist: pandas>=2.0.0; extra == "all"
Dynamic: author
Dynamic: home-page
Dynamic: license-file
Dynamic: requires-python
